pandalchemy/.DS_Store
pandalchemy/__init__.py
pandalchemy/__main__.py
pandalchemy/_version.py
pandalchemy/async_base.py
pandalchemy/async_connection_manager.py
pandalchemy/async_operations.py
pandalchemy/async_retry.py
pandalchemy/change_tracker.py
pandalchemy/cli.py
pandalchemy/conflict_resolution.py
pandalchemy/exceptions.py
pandalchemy/execution_plan.py
pandalchemy/interfaces.py
pandalchemy/pandalchemy_base.py
pandalchemy/pk_utils.py
pandalchemy/sql_operations.py
pandalchemy/tracked_dataframe.py
pandalchemy/utils.py
pandalchemy/tests/__init__.py
pandalchemy/tests/table_test.db
pandalchemy-1.6.0.dist-info/licenses/AUTHORS.rst
pandalchemy-1.6.0.dist-info/licenses/LICENSE
pandalchemy-1.6.0.dist-info/METADATA
pandalchemy-1.6.0.dist-info/WHEEL
pandalchemy-1.6.0.dist-info/entry_points.txt
pandalchemy-1.6.0.dist-info/top_level.txt
pandalchemy-1.6.0.dist-info/RECORD
