Metadata-Version: 2.4
Name: pandalchemy
Version: 1.6.0
Summary: A package that integrates pandas and sqlalchemy with change tracking and optimized SQL operations.
Author-email: Odos Matthews <odosmatthews@gmail.com>
License: MIT
Project-URL: Homepage, https://github.com/eddiethedean/pandalchemy
Project-URL: Documentation, https://github.com/eddiethedean/pandalchemy#readme
Project-URL: Repository, https://github.com/eddiethedean/pandalchemy
Project-URL: Issues, https://github.com/eddiethedean/pandalchemy/issues
Project-URL: Changelog, https://github.com/eddiethedean/pandalchemy/blob/main/CHANGELOG.rst
Classifier: Programming Language :: Python :: 3
Classifier: Programming Language :: Python :: 3.9
Classifier: Programming Language :: Python :: 3.10
Classifier: Programming Language :: Python :: 3.11
Classifier: Programming Language :: Python :: 3.12
Classifier: License :: OSI Approved :: MIT License
Classifier: Operating System :: OS Independent
Requires-Python: >=3.9
License-File: LICENSE
License-File: AUTHORS.rst
Requires-Dist: pandas>=1.5.0
Requires-Dist: sqlalchemy>=2.0.0
Requires-Dist: fullmetalalchemy>=2.4.0
Requires-Dist: transmutation>=1.1.0
Requires-Dist: numpy>=1.20.0
Provides-Extra: dev
Requires-Dist: pytest>=7.0.0; extra == "dev"
Requires-Dist: pytest-cov>=4.0.0; extra == "dev"
Requires-Dist: pytest-asyncio>=0.21.0; extra == "dev"
Requires-Dist: pytest-green-light>=0.2.0; extra == "dev"
Requires-Dist: pytest-xdist>=3.0.0; extra == "dev"
Requires-Dist: black>=23.0.0; extra == "dev"
Requires-Dist: mypy>=1.0.0; extra == "dev"
Requires-Dist: ruff>=0.1.0; extra == "dev"
Requires-Dist: aiosqlite>=0.19.0; extra == "dev"
Requires-Dist: asyncpg>=0.29.0; extra == "dev"
Requires-Dist: aiomysql>=0.2.0; extra == "dev"
Requires-Dist: greenlet>=2.0.0; extra == "dev"
Requires-Dist: psycopg2-binary>=2.9.0; extra == "dev"
Requires-Dist: pymysql>=1.0.0; extra == "dev"
Requires-Dist: testing.postgresql>=1.3.0; extra == "dev"
Requires-Dist: testing.mysqld>=1.4.0; extra == "dev"
Provides-Extra: async
Requires-Dist: aiosqlite>=0.19.0; extra == "async"
Requires-Dist: asyncpg>=0.29.0; extra == "async"
Requires-Dist: aiomysql>=0.2.0; extra == "async"
Requires-Dist: greenlet>=2.0.0; extra == "async"
Dynamic: license-file
